dispersionrelations/__init__.py
dispersionrelations/constants.py
dispersionrelations/dynamics.py
dispersionrelations/integrals.py
dispersionrelations/kinematics.py
dispersionrelations/plotting.py
dispersionrelations/utils.py
dispersionrelations-1.0.0.dist-info/licenses/LICENSE
dispersionrelations-1.0.0.dist-info/METADATA
dispersionrelations-1.0.0.dist-info/WHEEL
dispersionrelations-1.0.0.dist-info/top_level.txt
dispersionrelations-1.0.0.dist-info/RECORD
