Metadata-Version: 2.4
Name: dispersionrelations
Version: 1.0.0
Summary: Physics package for dispersion relations
Author: George Chanturia
License-Expression: MIT
Project-URL: homepage, https://github.com/giochanturia/DispersionRelations
Project-URL: documentation, https://dispersionrelations.readthedocs.io/
Project-URL: source, https://github.com/giochanturia/DispersionRelations
Classifier: Programming Language :: Python :: 3
Classifier: Operating System :: OS Independent
Requires-Python: >=3.9
License-File: LICENSE
Requires-Dist: numpy
Requires-Dist: scipy
Requires-Dist: scikit-image
Requires-Dist: matplotlib
Provides-Extra: docs
Requires-Dist: sphinx; extra == "docs"
Requires-Dist: pydata-sphinx-theme; extra == "docs"
Requires-Dist: sphinx-rtd-theme; extra == "docs"
Requires-Dist: sphinx-copybutton; extra == "docs"
Requires-Dist: sphinxcontrib-bibtex; extra == "docs"
Requires-Dist: docutils; extra == "docs"
Provides-Extra: dev
Requires-Dist: pytest; extra == "dev"
Dynamic: license-file
